{"name":"Confloose","tagline":"The worst startup scripts ever","body":"Confloose\r\n=========\r\n\r\nA *confloose* (or \"loose configuration\") is a collection of the worst a startup\r\nscript can do for you.\r\n\r\nWhen someone leaves his computer without locking it, the tradition here is to\r\ninstall such scripts on his computer while he's away -- as such, a confloose is\r\na challenge (it makes you learn your unix environment the hard way), and a way\r\nto remind you to never leave your computer and/or data in public space without\r\nprotection.\r\n\r\nRules :\r\n-------\r\n1. Don't destroy user data.\r\n2. Don't steal user data.\r\n3. Be fun and creative.\r\n","google":"","note":"Don't delete this file! It's used internally to help with page regeneration."}